odoo9_addon_base_tier_validation-9.0.1.0.2-py2.7-nspkg.pth
odoo9_addon_base_tier_validation-9.0.1.0.2.dist-info/DESCRIPTION.rst
odoo9_addon_base_tier_validation-9.0.1.0.2.dist-info/METADATA
odoo9_addon_base_tier_validation-9.0.1.0.2.dist-info/RECORD
odoo9_addon_base_tier_validation-9.0.1.0.2.dist-info/WHEEL
odoo9_addon_base_tier_validation-9.0.1.0.2.dist-info/metadata.json
odoo9_addon_base_tier_validation-9.0.1.0.2.dist-info/namespace_packages.txt
odoo9_addon_base_tier_validation-9.0.1.0.2.dist-info/top_level.txt
odoo_addons/base_tier_validation/README.rst
odoo_addons/base_tier_validation/__init__.py
odoo_addons/base_tier_validation/__openerp__.py
odoo_addons/base_tier_validation/models/__init__.py
odoo_addons/base_tier_validation/models/tier_definition.py
odoo_addons/base_tier_validation/models/tier_review.py
odoo_addons/base_tier_validation/models/tier_validation.py
odoo_addons/base_tier_validation/security/ir.model.access.csv
odoo_addons/base_tier_validation/views/tier_definition_view.xml
odoo_addons/base_tier_validation/views/tier_review_view.xml
